mallickboy/__init__.py
mallickboy/hellow.py
mallickboy/rle.py
mallickboy/runtime.py
mylib/__init__.py
mylib/rle.py
mylib/runtime.py
mallickboy-0.1.0.dist-info/METADATA
mallickboy-0.1.0.dist-info/WHEEL
mallickboy-0.1.0.dist-info/entry_points.txt
mallickboy-0.1.0.dist-info/top_level.txt
mallickboy-0.1.0.dist-info/RECORD
